pyyield.cpython-310-darwin.so
pyyield-0.1.0.dist-info/LICENSE
pyyield-0.1.0.dist-info/METADATA
pyyield-0.1.0.dist-info/WHEEL
pyyield-0.1.0.dist-info/top_level.txt
pyyield-0.1.0.dist-info/RECORD
