Metadata-Version: 2.1
Name: pyyield
Version: 0.1.0
Summary: Simple C++ ::std::this_thread::yield() call for Python, when sleep() calls have unknown effects.
Author: Rasmus Larsson
License: GNU GENERAL PUBLIC LICENSE
Project-URL: homepage, https://github.com/Tirine/pyyield
Project-URL: documentation, https://github.com/Tirine/pyyield
Project-URL: source, https://github.com/Tirine/pyyield
Project-URL: download, https://github.com/Tirine/pyyield
Project-URL: tracker, https://github.com/Tirine/pyyield/issues
Project-URL: release notes, https://github.com/Tirine/pyyield/releases
Classifier: Intended Audience :: Developers
Classifier: Programming Language :: C++
Classifier: Topic :: Software Development
Classifier: Operating System :: Unix
Classifier: Operating System :: POSIX
Classifier: Operating System :: Microsoft :: Windows
Classifier: Operating System :: MacOS
License-File: LICENSE
